aio_rabbitmq/__init__.py
aio_rabbitmq/__version__.py
aio_rabbitmq/rabbitmq.py
aio_rabbitmq/settings.py
aio_rabbitmq-0.0.94.dist-info/LICENSE
aio_rabbitmq-0.0.94.dist-info/METADATA
aio_rabbitmq-0.0.94.dist-info/WHEEL
aio_rabbitmq-0.0.94.dist-info/top_level.txt
aio_rabbitmq-0.0.94.dist-info/RECORD
