Metadata-Version: 2.1
Name: aio-rabbitmq
Version: 0.0.94
Summary: A concise library built on aio-pika for publishing and consuming from a message queue in RabbitMQ
Home-page: https://github.com/Nezhinskiy/aio-rabbitmq
Author: Nezhinskiy
Author-email: mikhail.nezhinsky@gmail.com
License: MIT
Keywords: aio_rabbitmq,rabbitmq,rabbit,aio-rabbit,rabbit-python,aio-pika,aiormq
Classifier: License :: OSI Approved :: MIT License
Classifier: Programming Language :: Python
Classifier: Programming Language :: Python :: 3
Classifier: Programming Language :: Python :: 3.7
Classifier: Programming Language :: Python :: 3.8
Classifier: Programming Language :: Python :: 3.9
Classifier: Programming Language :: Python :: 3.10
Classifier: Programming Language :: Python :: Implementation :: CPython
License-File: LICENSE
Requires-Dist: aio-pika >=9.3.0
